hairpred/models/rf_bestmodel_pssm.pkl
hairpred/models/rf_bestmodel_rsa.pkl
hairpred/python_script/__init__.py
hairpred/python_script/hairpred.py
hairpred-1.0.0.dist-info/LICENSE.txt
hairpred-1.0.0.dist-info/METADATA
hairpred-1.0.0.dist-info/WHEEL
hairpred-1.0.0.dist-info/entry_points.txt
hairpred-1.0.0.dist-info/top_level.txt
hairpred-1.0.0.dist-info/RECORD
