Metadata-Version: 2.1
Name: hairpred
Version: 1.0.0
Summary: HAIRPred: A tool for predicting,and designing of antibody binding residues
Home-page: https://github.com/RuchirSahni/HAIRpr
Author: Prof. G.P.S. Raghava
Author-email: raghava@iiitd.ac.in
Requires-Python: >=3.6
License-File: LICENSE.txt
Requires-Dist: numpy
Requires-Dist: pandas
Requires-Dist: scikit-learn
Requires-Dist: argparse
Requires-Dist: tqdm
